{"produtos":[{"id":1,"nome":"Smartphone","descricao":"Smartphone samsung galaxy a53 5g","preco":2500},{"id":2,"nome":"Smartphone","descricao":"Smartphone Iphone 13","preco":3200},{"id":3,"nome":"Smartphone","descricao":"Smartphone samsung galaxy a23","preco":1500},{"id":4,"nome":"Smartphone","descricao":"Smartphone samsung galaxy m62","preco":1800},{"id":5,"nome":"Smartphone","descricao":"Smartphone Iphone X","preco":2500},{"nome":"camiseta","description":"Camiseta de algodão azul","preco":30,"categoria_id":3,"imagem":"camiseta.jpg","id":"2a1cfa0e-53ab-4458-a23e-534d853fe477"},{"nome":"camiseta","description":"Camiseta de algodão azul","preco":30,"categoria_id":3,"imagem":"camiseta.jpg","id":"a056c687-4a84-4201-9171-ed43d045ff67"},{"nome":"camiseta","description":"Camiseta de algodão azul","preco":30,"categoria_id":3,"imagem":"camiseta.jpg","id":"d683493f-9297-4039-be51-07f82f44ff52"},{"nome":"camiseta","description":"Camiseta de algodão azul","preco":30,"categoria_id":3,"imagem":"camiseta.jpg","id":"7f5aa9f6-f3dc-4f03-9ebc-82fe4796c44b"},{"nome":"camiseta","description":"Camiseta de algodão azul","preco":30,"categoria_id":3,"imagem":"camiseta.jpg","id":"ea2dac61-9fc0-4c2d-93f5-da499220c423"},{"nome":"camiseta","description":"Camiseta de algodão azul","preco":30,"categoria_id":3,"imagem":"camiseta.jpg","id":"39b352e4-7d61-4e83-93d5-8bbf44497972"},{"nome":"camiseta","description":"Camiseta de algodão azul","preco":30,"categoria_id":3,"imagem":"camiseta.jpg","id":"2291ef65-3280-4ed7-9bf2-c252a6f31d2d"},{"nome":"camiseta","description":"Camiseta de algodão azul","preco":30,"categoria_id":3,"imagem":"camiseta.jpg","id":"cdaa7ad1-f595-4798-a6f2-d6ab96bd2b30"},{"nome":"camiseta","description":"Camiseta de algodão azul","preco":30,"categoria_id":3,"imagem":"camiseta.jpg","id":"bfd9d188-c373-42f0-b39c-617c22bc3f2e"}]}